fast_agent/__init__.py
fast_agent/config.py
fast_agent/constants.py
fast_agent/context.py
fast_agent/context_dependent.py
fast_agent/core.py
fast_agent/event_progress.py
fast_agent/interfaces.py
fast_agent/mcp_server_registry.py
fast_agent/py.typed
fast_agent/agents/__init__.py
fast_agent/agents/agent_types.py
fast_agent/agents/llm_agent.py
fast_agent/agents/llm_decorator.py
fast_agent/agents/mcp_agent.py
fast_agent/agents/tool_agent.py
fast_agent/agents/workflow/chain_agent.py
fast_agent/agents/workflow/evaluator_optimizer.py
fast_agent/agents/workflow/iterative_planner.py
fast_agent/agents/workflow/orchestrator_agent.py
fast_agent/agents/workflow/orchestrator_models.py
fast_agent/agents/workflow/orchestrator_prompts.py
fast_agent/agents/workflow/parallel_agent.py
fast_agent/agents/workflow/router_agent.py
fast_agent/cli/__init__.py
fast_agent/cli/__main__.py
fast_agent/cli/constants.py
fast_agent/cli/main.py
fast_agent/cli/terminal.py
fast_agent/cli/commands/check_config.py
fast_agent/cli/commands/go.py
fast_agent/cli/commands/quickstart.py
fast_agent/cli/commands/server_helpers.py
fast_agent/cli/commands/setup.py
fast_agent/cli/commands/url_parser.py
fast_agent/human_input/__init__.py
fast_agent/human_input/elicitation_handler.py
fast_agent/human_input/elicitation_state.py
fast_agent/human_input/form_fields.py
fast_agent/human_input/simple_form.py
fast_agent/human_input/types.py
fast_agent/llm/__init__.py
fast_agent/llm/fastagent_llm.py
fast_agent/llm/memory.py
fast_agent/llm/model_database.py
fast_agent/llm/model_factory.py
fast_agent/llm/prompt_utils.py
fast_agent/llm/provider_key_manager.py
fast_agent/llm/provider_types.py
fast_agent/llm/request_params.py
fast_agent/llm/sampling_converter.py
fast_agent/llm/usage_tracking.py
fast_agent/llm/internal/passthrough.py
fast_agent/llm/internal/playback.py
fast_agent/llm/internal/silent.py
fast_agent/llm/internal/slow.py
fast_agent/llm/provider/anthropic/anthropic_utils.py
mseep_fast_agent_mcp-0.3.1.dist-info/METADATA
mseep_fast_agent_mcp-0.3.1.dist-info/WHEEL
mseep_fast_agent_mcp-0.3.1.dist-info/entry_points.txt
mseep_fast_agent_mcp-0.3.1.dist-info/licenses/LICENSE
mseep_fast_agent_mcp-0.3.1.dist-info/RECORD
