Metadata-Version: 2.4
Name: mseep-fast-agent-mcp
Version: 0.3.1
Summary: Define, Prompt and Test MCP enabled Agents and Workflows
Author-email: mseep <support@skydeck.ai>
License:                                  Apache License
License-File: LICENSE
Classifier: License :: OSI Approved :: Apache Software License
Classifier: Operating System :: OS Independent
Classifier: Programming Language :: Python :: 3
Requires-Python: >=3.13
Requires-Dist: a2a-sdk>=0.3.0
Requires-Dist: aiohttp>=3.11.13
Requires-Dist: anthropic>=0.66.0
Requires-Dist: azure-identity>=1.14.0
Requires-Dist: boto3>=1.35.0
Requires-Dist: deprecated>=1.2.18
Requires-Dist: email-validator>=2.2.0
Requires-Dist: fastapi>=0.115.6
Requires-Dist: google-genai>=1.33.0
Requires-Dist: mcp==1.13.1
Requires-Dist: openai>=1.106.1
Requires-Dist: opentelemetry-distro>=0.55b0
Requires-Dist: opentelemetry-exporter-otlp-proto-http>=1.7.0
Requires-Dist: opentelemetry-instrumentation-anthropic>=0.43.1; python_version >= '3.10' and python_version < '4.0'
Requires-Dist: opentelemetry-instrumentation-google-genai>=0.3b0
Requires-Dist: opentelemetry-instrumentation-mcp>=0.43.1; python_version >= '3.10' and python_version < '4.0'
Requires-Dist: opentelemetry-instrumentation-openai>=0.43.1; python_version >= '3.10' and python_version < '4.0'
Requires-Dist: prompt-toolkit>=3.0.51
Requires-Dist: pydantic-settings>=2.7.0
Requires-Dist: pydantic>=2.10.4
Requires-Dist: pyperclip>=1.9.0
Requires-Dist: pyyaml>=6.0.2
Requires-Dist: rich>=14.1.0
Requires-Dist: tensorzero>=2025.7.5
Requires-Dist: typer>=0.15.1
